pyurlquerycli/__init__.py
pyurlquerycli/pyurlquerycli.py
pyurlquerycli/requirements.txt
pyurlquerycli-1.5.dist-info/METADATA
pyurlquerycli-1.5.dist-info/WHEEL
pyurlquerycli-1.5.dist-info/entry_points.txt
pyurlquerycli-1.5.dist-info/top_level.txt
pyurlquerycli-1.5.dist-info/RECORD
