Metadata-Version: 2.4
Name: pyurlquerycli
Version: 1.5
Summary: A simple Python script to interact with urlquery.net APIs from CLI
Author-email: tdebize@mail.com
License-Expression: LGPL-3.0-or-later
Project-URL: Homepage, https://github.com/maaaaz/pyurlquerycli/
Keywords: urlquery,url,malware,phishing,analyze,sandbox,api,cli
Classifier: Topic :: Security
Classifier: Programming Language :: Python :: 3
Requires-Python: >=3
Requires-Dist: requests
Requires-Dist: w3lib
Requires-Dist: validators
